[{
  "alohomora": -0.15555555555555556
}, {
  "locomotormortis": -0.6
}, {
  "petrificustotalus": -0.2636363636363636
}, {
  "wingardiumleviosa": -0.19999999999999998
}, {
  "aparecium": -0.4
}, {
  "eatslugs": -0.6
}, {
  "expelliarmus": -0.10799999999999998
}, {
  "homorphus": -0.1
}, {
  "lumos": -0.25909090909090904
}, {
  "obliviate": 6.938893903907228e-18
}, {
  "peskipiksipesternomi": -0.4
}, {
  "rictusempra": -0.3
}, {
  "serpensortia": 0.1
}, {
  "tarantallegra": -0.45
}, {
  "confundus": 0.16666666666666666
}, {
  "dissendium": -0.09999999999999999
}, {
  "expectopatronum": -0.1823529411764706
}, {
  "ferula": -0.1
}, {
  "fidelius": -0.044444444444444446
}, {
  "impervius": -0.016666666666666663
}, {
  "mobiliarbus": 0.1
}, {
  "mobilicorpus": 0.3
}, {
  "nox": -0.55
}, {
  "riddikulus": -0.046666666666666676
}, {
  "waddiwasi": -0.6
}, {
  "accio": -0.11176470588235295
}, {
  "avadakedavra": -0.2857142857142857
}, {
  "avis": 0.1
}, {
  "conjunctivitis": -0.1
}, {
  "crucio": -0.18666666666666668
}, {
  "deletrius": -0.2
}, {
  "densaugeo": 0.0
}, {
  "diffindo": -0.36666666666666664
}, {
  "engorgio": -0.09999999999999999
}, {
  "furnunculus": 0.0
}, {
  "impedimenta": -0.23076923076923073
}, {
  "imperio": 0.1125
}, {
  "incendio": -0.3
}, {
  "morsmordre": 0.0
}, {
  "orchideous": 0.4
}, {
  "pointme": 0.0
}, {
  "priorincantato": 0.0
}, {
  "quietus": 0.4
}, {
  "reducio": -0.55
}, {
  "reducto": 0.02499999999999998
}, {
  "relashio": -0.28
}, {
  "rennervate": -0.33999999999999997
}, {
  "reparo": 0.45999999999999996
}, {
  "sonorus": 0.19999999999999998
}, {
  "stupefy": -0.2
}, {
  "colloportus": -0.26666666666666666
}, {
  "flagrate": 0.0
}, {
  "incarcerous": 0.0
}, {
  "legilimens": -0.05714285714285715
}, {
  "protego": 0.06999999999999999
}, {
  "silencio": -0.25
}, {
  "aguamenti": -0.13
}, {
  "anapneo": -0.6
}, {
  "episkey": -0.6000000000000001
}, {
  "langlock": -0.5
}, {
  "levicorpus": -0.01999999999999999
}, {
  "liberacorpus": -0.2
}, {
  "muffliato": -0.19999999999999998
}, {
  "oppugno": 0.0
}, {
  "sectumsempra": -0.08749999999999998
}, {
  "specialisrevelio": -0.09999999999999999
}, {
  "tergeo": 0.10000000000000002
}, {
  "caveinimicum": 0.1
}, {
  "confringo": -0.05000000000000002
}, {
  "defodio": 0.0
}, {
  "deprimo": 0.0
}, {
  "duro": -0.5
}, {
  "erecto": -0.3
}, {
  "expulso": -0.6
}, {
  "geminio": 0.0
}, {
  "glisseo": 0.0
}, {
  "homenumrevelio": -0.35000000000000003
}, {
  "meteolojinxrecanto": -0.05
}, {
  "obscuro": -0.5
}, {
  "piertotumlocomotor": 0.4
}, {
  "protegohorribilis": 0.1
}, {
  "protegototalum": -0.1
}, {
  "repellomuggletum": 0.0
}, {
  "salviohexia": -0.1
}]
